zenduty_airflow_operator.py
zenduty_airflow_operator-0.1.2.dist-info/LICENSE
zenduty_airflow_operator-0.1.2.dist-info/METADATA
zenduty_airflow_operator-0.1.2.dist-info/WHEEL
zenduty_airflow_operator-0.1.2.dist-info/top_level.txt
zenduty_airflow_operator-0.1.2.dist-info/RECORD
