Metadata-Version: 2.1
Name: zenduty-airflow-operator
Version: 0.1.2
Summary: This Airflow plugin creates a Zenduty Alert when it is run.
Home-page: https://github.com/Zenduty/zenduty_airflow_plugin
Author: Nikhil Prem
Author-email: nikhil@zenduty.com
License: MIT License
Project-URL: Bug Tracker, https://github.com/Zenduty/zenduty_airflow_plugin/issues
Platform: UNKNOWN
License-File: LICENSE
Requires-Dist: zenduty-api
